stockcandle/__init__.py
stockcandle/intradayData.py
stockcandle-0.2.dist-info/LICENSE
stockcandle-0.2.dist-info/METADATA
stockcandle-0.2.dist-info/WHEEL
stockcandle-0.2.dist-info/top_level.txt
stockcandle-0.2.dist-info/RECORD
