Metadata-Version: 2.1
Name: stockcandle
Version: 0.2
Summary: Python library to fetch intraday data for any given EQ symbol
Home-page: https://github.com/ranjanrak/stockcandle.git
Author: Rakesh R
Author-email: rrrakesh265@gmail.com
License: MIT
Platform: UNKNOWN
Classifier: Programming Language :: Python :: 3
Classifier: License :: OSI Approved :: MIT License
Classifier: Topic :: Software Development :: Libraries
Requires-Dist: requests
